audio-feature/__init__.py
audio-feature/compute_fbank.py
audio-feature/compute_melspectrogram.py
audio_feature/__init__.py
audio_feature/batch_compute.py
audio_feature/compute_fbank.py
audio_feature/compute_melspectrogram.py
audio_feature/main.py
audio_feature-0.1.0.dist-info/METADATA
audio_feature-0.1.0.dist-info/WHEEL
audio_feature-0.1.0.dist-info/entry_points.txt
audio_feature-0.1.0.dist-info/top_level.txt
audio_feature-0.1.0.dist-info/RECORD
