Metadata-Version: 2.1
Name: audio-feature
Version: 0.1.0
Summary: get features from wav
Author: AaronLi
Author-email: 1470409562@qq.com
License: apache 3.0
Requires-Dist: torchaudio
Requires-Dist: numpy
Requires-Dist: tqdm
Requires-Dist: joblib
Requires-Dist: loguru
